mbase/__init__.py
mbase/eventlog.py
mbase/exceptions.py
mbase/future.py
mbase/mlogging.py
mbase/models.py
mbase/services.py
mbase/utils.py
moneyflow_base-0.0.5.dist-info/LICENSE
moneyflow_base-0.0.5.dist-info/WHEEL
moneyflow_base-0.0.5.dist-info/METADATA
moneyflow_base-0.0.5.dist-info/RECORD
