Metadata-Version: 2.1
Name: moneyflow-base
Version: 0.0.5
Summary: Moneyflow Base
Author-email: Team Moneyflow <infrastructure@moneyflow.io>
Requires-Python: >=3.10
Classifier: Programming Language :: Python :: 3
Classifier: License :: OSI Approved :: MIT License
Classifier: Operating System :: OS Independent
Requires-Dist: structlog
Requires-Dist: django
Requires-Dist: dramatiq
Requires-Dist: redis
Project-URL: Bug Tracker, https://github.com/moneyflow-group/moneyflow-base/issues
Project-URL: Homepage, https://github.com/moneyflow-group/moneyflow-base
